vdf/__init__.py
vdf/vdict.py
vdf-3.3.dist-info/LICENSE
vdf-3.3.dist-info/METADATA
vdf-3.3.dist-info/WHEEL
vdf-3.3.dist-info/top_level.txt
vdf-3.3.dist-info/zip-safe
vdf-3.3.dist-info/RECORD
