Metadata-Version: 1.1
Name: vdf
Version: 3.3
Summary: Library for working with Valve's VDF text format
Home-page: https://github.com/ValvePython/vdf
Author: Rossen Georgiev
Author-email: rossen@rgp.io
License: MIT
Keywords: valve keyvalue vdf tf2 dota2 csgo
Platform: UNKNOWN
Classifier: Development Status :: 5 - Production/Stable
Classifier: Intended Audience :: Developers
Classifier: License :: OSI Approved :: MIT License
Classifier: Topic :: Software Development :: Libraries :: Python Modules
Classifier: Natural Language :: English
Classifier: Operating System :: OS Independent
Classifier: Programming Language :: Python :: 2.7
Classifier: Programming Language :: Python :: 3
Classifier: Programming Language :: Python :: 3.3
Classifier: Programming Language :: Python :: 3.4
Classifier: Programming Language :: Python :: 3.5
Classifier: Programming Language :: Python :: Implementation :: PyPy
